{
  "passage": "Apocalypse 2.1-7",
  "date": "2026-06-19",
  "pastor_name": "AGB",
  "church_name": "EBC",
  "passage_context": "Apocalypse 2.1-7 ouvre la deuxième grande division du livre. Selon le plan que Christ lui-même dicte en 1.19, l'Apocalypse se compose de trois volets: « ce que tu as vu » (le Christ glorifié du chapitre 1), « ce qui est » (les sept lettres aux Églises, chapitres 2 et 3) et « ce qui doit arriver ensuite » (la révélation de l'avenir, chapitres 4 à 22). La lettre à Éphèse inaugure donc la section « ce qui est ». Elle n'est pas une parabole codée de l'histoire de l'Église ni une allégorie spiritualisée: c'est une missive réelle, adressée à une assemblée historique précise d'Asie Mineure, que Jean connaissait intimement pour y avoir exercé son ministère avant son exil à Patmos. MacArthur souligne pourtant que ces sept Églises, tout en étant des assemblées effectivement établies, représentent aussi des types d'Églises que l'on retrouve à toutes les époques de l'ère présente; le message de Christ leur est donc pertinent en tout temps. La grille de lecture demeure futuriste, grammatico-historique et littérale: rien ici n'autorise à transformer ces lettres en panorama prophétique d'âges successifs.\n\nLes sept lettres suivent toutes le même moule, et Éphèse en fournit le modèle inaugural. Christ se présente d'abord par un titre tiré de la vision du chapitre 1, ici « celui qui tient les sept étoiles dans sa main droite, celui qui marche au milieu des sept chandeliers d'or » (2.1). Vient ensuite le diagnostic souverain qui s'ouvre invariablement par « Je connais tes oeuvres », l'éloge de ce qui est fidèle (2.2-3, 6), le reproche du défaut central (2.4), l'appel à la repentance assorti d'un avertissement de jugement (2.5), puis la double clausule finale: l'exhortation « que celui qui a des oreilles entende ce que l'Esprit dit aux Églises » et la promesse au vainqueur (2.7). Ce schéma révèle l'autorité du Seigneur ressuscité qui inspecte ses assemblées, les loue et les corrige.\n\nLe coeur de la lettre est un contraste douloureux. Éphèse est une Église irréprochable sur le plan doctrinal et moral: elle travaille, persévère, ne supporte pas les méchants, démasque les faux apôtres, ne s'est jamais lassée, hait les oeuvres des Nicolaïtes. Et pourtant le Seigneur a « contre elle » un grief décisif: « tu as abandonné ton premier amour » (2.4). C'est là l'idée maîtresse de la péricope et de toute la série: une orthodoxie sans faille ne remplace jamais l'amour pour Christ. La menace est extrême, l'enlèvement du chandelier, c'est-à-dire la fin même de l'Église comme témoin lumineux. La péricope inaugure ainsi l'appel à la repentance que Christ adresse aux Églises de tous les temps, et elle se referme sur l'espérance du vainqueur qui mangera de l'arbre de vie dans le paradis de Dieu.",
  "historical_background": "Éphèse était la métropole de l'Asie proconsulaire, surnommée la « porte d'entrée de l'Asie ». Située à environ cinq kilomètres de la mer, elle restait accessible par l'embouchure du fleuve Caystre et constituait le plus grand port de la région; placée au carrefour de quatre grandes voies commerciales, elle brassait richesses, idées et populations. Elle était surtout le centre du culte d'Artémis (la Diane des Romains), dont le temple comptait parmi les sept merveilles du monde antique. Cette idolâtrie spectaculaire, doublée de magie et de prostitution sacrée, explique l'âpreté du combat spirituel qui s'y livrait. Paul y exerça son ministère pendant près de trois ans (Ac 20.31), au point que selon Actes 19 toute l'Asie entendit la Parole et que les magiciens convertis brûlèrent publiquement leurs livres. Timothée, Tychique, puis l'apôtre Jean lui-même y servirent ensuite. C'est à Éphèse que Jean fut arrêté sous Domitien, avant d'être déporté à Patmos, à quelque quatre-vingts kilomètres de là.\n\nL'Église d'Éphèse jouissait donc d'un héritage spirituel exceptionnel. Fondée par Paul, instruite par les épîtres pauliniennes et les avertissements solennels des anciens (Ac 20.28-31, où Paul prédit l'arrivée de loups cruels), pastorée par Timothée et finalement par Jean, elle avait reçu un enseignement de premier ordre. MacArthur note qu'au moment où Jean écrit, vers 94 à 96 apr. J.-C. sous Domitien, cette Église était fidèle depuis plus de quarante ans. Cette ancienneté éclaire le déclin: la deuxième, voire la troisième génération de croyants avait hérité d'une doctrine pure mais avait laissé refroidir la ferveur des commencements. Le contexte de persécution montante, la pression du culte impérial et la nécessité d'un discernement constant face aux imposteurs avaient durci l'Église dans une vigilance défensive irréprochable, au prix de l'ardeur du premier amour.\n\nDeux menaces concrètes encadrent la lettre. D'abord les faux apôtres: des hommes se réclamaient d'une autorité apostolique qu'ils n'avaient pas, et l'Église les avait éprouvés et démasqués comme menteurs (2.2). Éphèse appliquait ainsi le test apostolique du discernement, conformément à l'exhortation paulinienne d'éprouver toutes choses (cf. 1 Th 5.20-21). Ensuite les Nicolaïtes (2.6), secte hérétique dont le nom signifie « vainqueur des peuples ». MacArthur rapporte la tradition d'Irénée selon laquelle Nicolas, l'un des sept choisis en Actes 6, aurait sombré dans l'apostasie et égaré des croyants; à la manière de Balaam, les Nicolaïtes poussaient à l'immoralité et aux festins idolâtres, pervertissant la grâce en licence. Clément d'Alexandrie écrivit qu'ils s'adonnaient aux plaisirs sans retenue. Le développement même de cette secte, absente des épîtres pauliniennes adressées aux mêmes Églises, confirme une rédaction tardive de l'Apocalypse, à la fin du règne de Domitien, et non sous Néron.",
  "word_studies": [
    {
      "english": "chandeliers",
      "transliteration": "luchnia",
      "literal_meaning": "porte-lampe, support sur lequel on pose la lampe à huile pour qu'elle éclaire",
      "range_of_meaning": "Le mot ne désigne pas la lampe elle-même mais le support qui l'élève et la rend visible. Christ marche « au milieu des sept chandeliers d'or » (2.1), et 1.20 en donne la clé: les sept chandeliers sont les sept Églises. MacArthur explique que ces chandeliers portatifs en or, munis de petites lampes à huile, représentent chaque assemblée comme porteuse de la lumière de la vie; le chiffre sept symbolise la plénitude, la totalité des Églises. L'Église n'est pas la source de la lumière, elle en est le support: sa raison d'être est de faire briller Christ. Ôter le chandelier (2.5), c'est retirer ce témoignage lumineux, donc faire cesser l'Église.",
      "translations": {
        "S21": "chandeliers",
        "NEG79": "chandeliers",
        "Darby": "lampes",
        "LSG": "chandeliers",
        "KJF": "chandeliers"
      }
    },
    {
      "english": "œuvres",
      "transliteration": "erga",
      "literal_meaning": "actes, ouvrages, ce qui est effectivement accompli et produit par la vie",
      "range_of_meaning": "Pluriel d'ergon. Christ ouvre son diagnostic par « Je connais tes oeuvres » (2.2), formule récurrente des sept lettres, et appelle Éphèse à « pratiquer ses premières oeuvres » (2.5). Pour MacArthur, les oeuvres ne sont jamais le prix du salut mais la preuve visible de la foi authentique: ici elles attestent une activité réelle (travail, persévérance, discernement). Or des oeuvres correctes peuvent subsister alors que l'amour s'est éteint; c'est le drame d'Éphèse. Le Seigneur connaît les oeuvres parce qu'il connaît les coeurs (cf. 2.23), et il jugera les Églises selon ce regard infaillible. Les oeuvres comptent, mais elles ne remplacent pas le coeur qui les motive.",
      "translations": {
        "S21": "œuvres",
        "NEG79": "œuvres",
        "Darby": "œuvres",
        "LSG": "œuvres",
        "KJF": "œuvres"
      }
    },
    {
      "english": "abandonné",
      "transliteration": "aphiemi",
      "literal_meaning": "laisser aller, lâcher, délaisser, abandonner volontairement ce que l'on tenait",
      "range_of_meaning": "Verbe employé en 2.4: « tu as abandonné ton premier amour ». Le terme n'évoque pas une perte accidentelle mais un relâchement, un délaissement: on a laissé filer ce qu'on possédait. MacArthur précise que la ferveur et la passion des Éphésiens pour Christ s'étaient muées en une orthodoxie froide et mécanique; leur pureté morale et doctrinale, leur zèle pour la vérité et leur service discipliné ne pouvaient remplacer l'amour pour Christ qu'ils avaient perdu. Le temps grec marque un état actuel résultant d'un acte révolu: ils ont délaissé, et ils demeurent dans cet abandon. D'où l'appel à se souvenir, à se repentir et à refaire les premières oeuvres (2.5).",
      "translations": {
        "S21": "abandonné",
        "NEG79": "abandonné",
        "Darby": "abandonné",
        "LSG": "abandonné",
        "KJF": "abandonné"
      }
    },
    {
      "english": "premier",
      "transliteration": "protos",
      "literal_meaning": "premier, du commencement, originel, de tout premier rang",
      "range_of_meaning": "Adjectif qualifiant l'amour (2.4) et, sous une autre forme, les « premières oeuvres » (2.5). Il renvoie à l'amour des origines, l'ardeur fraîche et entière des nouveaux convertis pour leur Sauveur. MacArthur rappelle qu'être chrétien, c'est aimer le Seigneur Jésus-Christ (Jn 14.21, 23; 1 Co 16.22): cet amour n'est pas un sentiment accessoire mais la marque même de la foi véritable. Le « premier amour » n'est donc pas un degré supérieur réservé à une élite spirituelle, mais le climat normal de toute conversion authentique. Le perdre, c'est dériver vers une religion de devoir sans dévotion. Le remède n'est pas un nouvel amour, mais le retour au premier.",
      "translations": {
        "S21": "premier",
        "NEG79": "premier",
        "Darby": "premier",
        "LSG": "premier",
        "KJF": "premier"
      }
    },
    {
      "english": "vaincra",
      "transliteration": "nikao",
      "literal_meaning": "vaincre, l'emporter, remporter la victoire, être vainqueur",
      "range_of_meaning": "Verbe de la victoire, employé dans la promesse finale de chacune des sept lettres (2.7, 11, 17, 26; 3.5, 12, 21). « À celui qui vaincra je donnerai à manger de l'arbre de vie. » MacArthur, suivant la définition johannique de 1 Jean 5.4-5, soutient que le vainqueur n'est pas un chrétien d'élite mais tout chrétien véritable: la foi qui s'empare de Christ est elle-même la victoire qui triomphe du monde. La promesse n'est donc pas un prix gagné par la performance, mais la part assurée de quiconque appartient réellement à Christ. Le vocabulaire de la victoire répond ironiquement au nom des Nicolaïtes (« vainqueurs des peuples »): le vrai vainqueur n'est pas celui qui asservit, mais celui qui persévère dans la foi jusqu'à hériter la vie.",
      "translations": {
        "S21": "vaincra",
        "NEG79": "vaincra",
        "Darby": "vaincra",
        "LSG": "vaincra",
        "KJF": "vaincra"
      }
    }
  ],
  "commentary_insights": "MacArthur lit Apocalypse 2.1-7 comme la première démonstration de l'autorité souveraine du Christ glorifié sur son Église. Le titre d'ouverture est tout sauf décoratif: « celui qui tient les sept étoiles dans sa main droite, celui qui marche au milieu des sept chandeliers d'or ». Les sept étoiles, selon 1.16 et 1.20, sont les messagers qui représentent les sept Églises, et le fait que Christ les tienne dans sa main signifie qu'il contrôle l'Église et ses dirigeants. Le verbe « marche » présente un Seigneur qui n'est pas absent ni distant mais qui circule au milieu de ses assemblées, les inspectant de près. Sur l'identité de « l'ange » de chaque Église (2.1), MacArthur tranche: le mot signifie littéralement « messager », et puisque les anges célestes ne sont jamais responsables d'Églises, il s'agit ici de l'ancien dirigeant ou du pasteur qui représente l'assemblée et reçoit la lettre. La lentille demeure cessationniste et grammatico-historique: aucune révélation continue, le canon parle.\n\nLe diagnostic est d'une lucidité redoutable parce qu'il vient de celui qui connaît tout. « Je connais tes oeuvres »: Christ commence par un éloge sincère et détaillé. Éphèse travaille dur, persévère, refuse de tolérer les méchants, a éprouvé les prétendus apôtres et les a démasqués comme menteurs, a souffert pour le nom de Christ sans se lasser pendant plus de quarante ans. MacArthur insiste sur la qualité de ce discernement: cette Église savait évaluer doctrine et conduite, conformément au devoir d'éprouver toutes choses (cf. 1 Th 5.20-21). Elle haïssait même les oeuvres des Nicolaïtes, que Christ hait aussi, cette secte antinomienne qui, à la manière de Balaam, transformait la grâce en licence et poussait à l'immoralité et à l'idolâtrie. Sur le plan de l'orthodoxie et de la moralité, Éphèse était un modèle. C'est précisément ce qui rend le reproche si pénétrant.\n\nCar « j'ai contre toi que tu as abandonné ton premier amour » (2.4). MacArthur expose ici le coeur du texte: la ferveur et la passion des Éphésiens pour Christ étaient devenues une orthodoxie froide et mécanique. Leur pureté doctrinale, leur zèle pour la vérité et leur service discipliné ne pouvaient pas remplacer l'amour pour Christ qu'ils avaient perdu. Être chrétien, c'est aimer le Seigneur Jésus-Christ (Jn 14.21, 23; 1 Co 16.22); une foi qui cesse d'aimer son objet trahit sa propre nature. Le remède est précis et tient en trois impératifs (2.5): se souvenir d'où l'on est tombé (mesurer la chute par comparaison avec la hauteur d'origine), se repentir (changer radicalement de disposition), et pratiquer les premières oeuvres (reprendre les actes que produisait l'amour des débuts). L'avertissement est terrible: « sinon je viendrai à toi et j'ôterai ton chandelier de sa place. » MacArthur y voit la menace du jugement de Dieu amenant la fin même de l'Église d'Éphèse comme témoin. Une assemblée orthodoxe mais sans amour finit par perdre son droit d'exister.\n\nLa lettre se referme sur la double clausule. « Que celui qui a des oreilles entende ce que l'Esprit dit aux Églises »: la voix de Christ et celle de l'Esprit ne font qu'un, et le message vaut pour toutes les Églises de tous les temps, non pour Éphèse seule. Puis la promesse: « à celui qui vaincra je donnerai à manger de l'arbre de vie, qui est dans le paradis de Dieu. » MacArthur, à la lumière de 1 Jean 5.4-5, identifie le vainqueur à tout vrai croyant: vaincre n'est pas un exploit héroïque réservé à quelques-uns, c'est la marque normale de la foi authentique qui persévère. L'arbre de vie, perdu en Éden (Gn 2.9; 3.22-24) et retrouvé dans la nouvelle Jérusalem (Ap 22.2), symbolise la vie éternelle et les bénédictions éternelles promises aux vrais croyants. La cohérence Lordship est entière: l'appel à la repentance est réel et adressé à une Église, les oeuvres prouvent la foi sans la procurer, et la sécurité finale appartient à celui qui vainc parce qu'il appartient à Christ. La promesse répond ironiquement au nom des Nicolaïtes: le seul véritable « vainqueur des peuples » est le croyant qui hérite la vie.",
  "cross_references": [
    {
      "reference": "Apocalypse 1.12-20",
      "connection": "Source directe des titres de 2.1: les sept chandeliers sont les Églises, les sept étoiles leurs messagers, et Christ qui les tient et marche parmi eux contrôle souverainement son Église.",
      "type": "Parallèle direct"
    },
    {
      "reference": "Actes 20.28-31",
      "connection": "Paul avertit les anciens d'Éphèse de l'arrivée de loups cruels et les exhorte à veiller; le discernement loué en 2.2-3 est l'héritage direct de cet avertissement pastoral.",
      "type": "Parallèle direct"
    },
    {
      "reference": "Jean 14.21-23",
      "connection": "Définition johannique: aimer Christ et garder sa parole sont inséparables; éclaire pourquoi l'abandon du premier amour (2.4) est un défaut mortel, non un détail affectif.",
      "type": "Parallèle direct"
    },
    {
      "reference": "1 Jean 5.4-5",
      "connection": "Définit le vainqueur (nikao) comme tout croyant né de Dieu dont la foi triomphe du monde; clé de lecture de la promesse au vainqueur en 2.7.",
      "type": "Parallèle direct"
    },
    {
      "reference": "Genèse 2.9; 3.22-24",
      "connection": "L'arbre de vie en Éden, dont l'accès fut barré après la chute; la promesse de 2.7 annonce son retour comme restauration de la vie éternelle perdue.",
      "type": "Arrière-plan AT"
    },
    {
      "reference": "Nombres 25.1-3 avec 31.16",
      "connection": "La ruse de Balaam entraînant Israël dans l'immoralité et l'idolâtrie; modèle vétérotestamentaire de l'hérésie nicolaïte haïe en 2.6.",
      "type": "Arrière-plan AT"
    },
    {
      "reference": "1 Thessaloniciens 5.20-21",
      "connection": "Le devoir d'éprouver toutes choses et de retenir ce qui est bon; fondement du discernement par lequel Éphèse démasque les faux apôtres (2.2).",
      "type": "Lien thématique"
    },
    {
      "reference": "Apocalypse 22.1-2, 14",
      "connection": "L'arbre de vie dans la nouvelle Jérusalem, accessible à ceux qui ont part au paradis de Dieu; accomplissement final de la promesse au vainqueur de 2.7.",
      "type": "Parallèle direct"
    }
  ],
  "theological_themes": [
    {
      "name": "La seigneurie inspectrice du Christ glorifié sur son Église",
      "in_text": "Christ « tient les sept étoiles dans sa main droite » et « marche au milieu des sept chandeliers d'or » (2.1), puis ouvre par « Je connais tes oeuvres » (2.2): il contrôle dirigeants et assemblées et les inspecte de près.",
      "implication": "L'Apocalypse est la révélation de Jésus-Christ glorifié, souverain absolu sur l'histoire et sur ses Églises. Aucune assemblée n'échappe à son regard ni à son autorité. Pour votre assemblée: Christ connaît réellement nos oeuvres et nos coeurs, et il nous évalue à sa mesure et non à la nôtre."
    },
    {
      "name": "L'orthodoxie ne remplace jamais l'amour pour Christ",
      "in_text": "Église irréprochable en doctrine et en moeurs (2.2-3, 6), Éphèse s'entend pourtant reprocher l'essentiel: « tu as abandonné ton premier amour » (2.4); la ferveur s'est muée en orthodoxie froide.",
      "implication": "Une foi authentique aime son objet; cesser d'aimer Christ trahit la foi elle-même (Jn 14.21; 1 Co 16.22). Pour votre assemblée: la justesse doctrinale et l'activité religieuse, bien que nécessaires, peuvent coexister avec un coeur refroidi; le danger n'est pas l'hérésie mais la tiédeur sous couvert de rigueur."
    },
    {
      "name": "L'appel réel à la repentance et le jugement du chandelier ôté",
      "in_text": "Trois impératifs, « souviens-toi, repens-toi, pratique tes premières oeuvres », assortis de la menace « j'ôterai ton chandelier de sa place » (2.5): le jugement de Dieu pouvant amener la fin de l'Église.",
      "implication": "Lordship: les appels à la repentance adressés aux sept Églises sont authentiques et urgents, non rhétoriques. Pour votre assemblée: une Église qui ne se repent pas de sa tiédeur peut perdre son témoignage et son existence même; la repentance n'est pas réservée aux incroyants, elle est la respiration du croyant."
    },
    {
      "name": "Les oeuvres preuve de la foi, jamais son prix",
      "in_text": "« Je connais tes oeuvres » et « pratique tes premières oeuvres » (2.2, 5): les oeuvres attestent une vie réelle, et le vainqueur de 2.7 est le vrai croyant dont la foi persévère.",
      "implication": "Les oeuvres démontrent le salut sans jamais le procurer (cf. Ja 2.14-26; Ap 2.23). Pour votre assemblée: l'examen de soi porte sur le fruit, mais la racine est la foi qui aime; refaire les premières oeuvres, c'est laisser l'amour retrouvé reproduire ses actes."
    },
    {
      "name": "La promesse au vainqueur: l'arbre de vie dans le paradis de Dieu",
      "in_text": "« À celui qui vaincra je donnerai à manger de l'arbre de vie, qui est dans le paradis de Dieu » (2.7): promesse de vie éternelle, l'arbre perdu en Éden et retrouvé dans la nouvelle Jérusalem.",
      "implication": "Le vainqueur est tout vrai croyant (1 Jn 5.4-5); la promesse est sa part assurée, gage de la sécurité éternelle des saints. Pour votre assemblée: l'espérance du croyant n'est pas un retour nostalgique mais la vie éternelle consommée dans le paradis de Dieu, ce qui rallume aujourd'hui l'amour qui persévère jusqu'au bout."
    }
  ],
  "thinking_prompts": [
    "Christ se présente comme celui qui marche au milieu des chandeliers et qui dit « Je connais tes oeuvres ». En quoi la conscience que le Seigneur inspecte réellement notre assemblée change-t-elle notre manière de servir cette semaine?",
    "Éphèse était irréprochable en doctrine et en moeurs, et pourtant reprise par Christ. Comment discerner, dans ma propre vie, si ma rigueur doctrinale est encore portée par l'amour ou si elle est devenue une orthodoxie froide et mécanique?",
    "Le « premier amour » est l'ardeur des commencements pour Christ. Quels signes concrets marquaient cet amour à ma conversion, et lesquels se sont-ils estompés sans que je m'en rende compte?",
    "Le remède tient en trois verbes: se souvenir, se repentir, pratiquer les premières oeuvres. Lequel des trois est-ce que je néglige le plus, et que serait, concrètement, le « refaire mes premières oeuvres »?",
    "L'avertissement « j'ôterai ton chandelier » menace l'existence même d'une Église tiède. Que dit cet avertissement aux Églises orthodoxes mais refroidies d'aujourd'hui, et à la nôtre en particulier?",
    "Éphèse haïssait à juste titre les oeuvres des Nicolaïtes. Comment tenir ensemble la haine du faux enseignement et l'amour fervent pour Christ, sans que le combat pour la vérité n'éteigne la dévotion?",
    "La promesse de manger de l'arbre de vie au vainqueur est offerte à tout vrai croyant. En quoi cette espérance de la vie éternelle dans le paradis de Dieu peut-elle, dès aujourd'hui, raviver un amour que la routine a refroidi?"
  ]
}
